lognub/__init__.py
lognub/captures/__init__.py
lognub/captures/python_exceptions.py
lognub/captures/python_warnings.py
lognub/client.py
lognub/handles/__init__.py
lognub/handles/_common.py
lognub/handles/intercept_handler.py
lognub/handles/propagate_handler.py
lognub/patchers/__init__.py
lognub/patchers/patch_loggers.py
lognub-0.2.1.dist-info/METADATA
lognub-0.2.1.dist-info/WHEEL
lognub-0.2.1.dist-info/RECORD
