Metadata-Version: 2.1
Name: lognub
Version: 0.2.1
Summary: Dumb Log Utlity for personal use
Home-page: https://github.com/ChethanUK/
License: Apache-2.0
Keywords: Loguru,data-ops,data-engineering,best-practices
Author: ChethanUK
Author-email: chethanuk@outlook.com
Maintainer: ChethanUK
Maintainer-email: chethanuk@outlook.com
Requires-Python: >=3.7.2,<4.0
Classifier: Development Status :: 4 - Beta
Classifier: Intended Audience :: Developers
Classifier: License :: OSI Approved :: Apache Software License
Classifier: Natural Language :: English
Classifier: Operating System :: OS Independent
Classifier: Programming Language :: Python :: 3
Classifier: Programming Language :: Python :: 3.8
Classifier: Programming Language :: Python :: 3.9
Classifier: Programming Language :: Python :: 3.10
Classifier: Programming Language :: Python :: 3.11
Classifier: Programming Language :: Python :: 3 :: Only
Classifier: Programming Language :: Python :: 3.7
Requires-Dist: loguru (>=0.7.0,<0.8.0)
Project-URL: Documentation, https://github.com/ChethanUK/lognub#readme
Project-URL: Repository, https://github.com/ChethanUK/lognub
